<?xml version="1.0" encoding="UTF-8"?>
<configuration>
    <!-- Console appender -->
    <appender name="CONSOLE" class="ch.qos.logback.core.ConsoleAppender">
        <encoder>
            <pattern>%d{yyyy-MM-dd HH:mm:ss.SSS} %highlight(%-5level) [%thread] %cyan(%logger{36}) - %msg%n</pattern>
        </encoder>
    </appender>

    <!-- File appender for all logs -->
    <appender name="FILE" class="ch.qos.logback.core.rolling.RollingFileAppender">
        <file>logs/crawler.log</file>
        <rollingPolicy class="ch.qos.logback.core.rolling.TimeBasedRollingPolicy">
            <fileNamePattern>logs/crawler.%d{yyyy-MM-dd}.log</fileNamePattern>
            <maxHistory>7</maxHistory>
            <totalSizeCap>100MB</totalSizeCap>
        </rollingPolicy>
        <encoder>
            <pattern>%d{yyyy-MM-dd HH:mm:ss.SSS} %-5level [%thread] %logger{36} - %msg%n</pattern>
        </encoder>
    </appender>

    <!-- Separate appender for errors -->
    <appender name="ERROR_FILE" class="ch.qos.logback.core.rolling.RollingFileAppender">
        <file>logs/crawler-error.log</file>
        <filter class="ch.qos.logback.classic.filter.ThresholdFilter">
            <level>ERROR</level>
        </filter>
        <rollingPolicy class="ch.qos.logback.core.rolling.TimeBasedRollingPolicy">
            <fileNamePattern>logs/crawler-error.%d{yyyy-MM-dd}.log</fileNamePattern>
            <maxHistory>30</maxHistory>
        </rollingPolicy>
        <encoder>
            <pattern>%d{yyyy-MM-dd HH:mm:ss.SSS} %-5level [%thread] %logger{36} - %msg%n%ex</pattern>
        </encoder>
    </appender>

    <!-- Async appender for better performance -->
    <appender name="ASYNC" class="ch.qos.logback.classic.AsyncAppender">
        <appender-ref ref="FILE"/>
        <queueSize>500</queueSize>
        <discardingThreshold>0</discardingThreshold>
    </appender>

    <!-- Logger configurations -->
    <logger name="com.crawler" level="DEBUG"/>
    <logger name="org.jsoup" level="WARN"/>
    <logger name="org.sqlite" level="WARN"/>

    <!-- Root logger -->
    <root level="INFO">
        <appender-ref ref="CONSOLE"/>
        <appender-ref ref="ASYNC"/>
        <appender-ref ref="ERROR_FILE"/>
    </root>
</configuration>
